{"pages":["custom.png"],"chars":[{"id":12385,"index":28668,"char":"ち","width":33,"height":41,"xoffset":3,"yoffset":2,"xadvance":42,"chnl":15,"x":0,"y":0,"page":0},{"id":12435,"index":28718,"char":"ん","width":39,"height":38,"xoffset":1,"yoffset":3,"xadvance":42,"chnl":15,"x":0,"y":42,"page":0},{"id":12399,"index":28682,"char":"は","width":38,"height":38,"xoffset":3,"yoffset":4,"xadvance":42,"chnl":15,"x":34,"y":0,"page":0},{"id":12395,"index":28678,"char":"に","width":37,"height":37,"xoffset":3,"yoffset":4,"xadvance":42,"chnl":15,"x":0,"y":81,"page":0},{"id":12371,"index":28654,"char":"こ","width":32,"height":31,"xoffset":5,"yoffset":8,"xadvance":42,"chnl":15,"x":0,"y":119,"page":0}],"info":{"face":"custom","size":42,"bold":0,"italic":0,"charset":["こ","ん","に","ち","は"],"unicode":1,"stretchH":100,"smooth":1,"aa":1,"padding":[2,2,2,2],"spacing":[0,0]},"common":{"lineHeight":45,"base":36,"scaleW":256,"scaleH":256,"pages":1,"packed":0,"alphaChnl":0,"redChnl":0,"greenChnl":0,"blueChnl":0},"distanceField":{"fieldType":"msdf","distanceRange":4},"kernings":[]}